hyper_fabric_interconnect-1.0.0.dist-info/licenses/LICENSE
hyperfabric/__init__.py
hyperfabric/_version.py
hyperfabric/buffers.py
hyperfabric/cli.py
hyperfabric/exceptions.py
hyperfabric/licensing.py
hyperfabric/nodes.py
hyperfabric/protocol.py
hyperfabric/routing.py
hyperfabric/topology.py
hyper_fabric_interconnect-1.0.0.dist-info/METADATA
hyper_fabric_interconnect-1.0.0.dist-info/WHEEL
hyper_fabric_interconnect-1.0.0.dist-info/entry_points.txt
hyper_fabric_interconnect-1.0.0.dist-info/top_level.txt
hyper_fabric_interconnect-1.0.0.dist-info/RECORD
