Metadata-Version: 2.4
Name: hyper-fabric-interconnect
Version: 1.0.0
Summary: Breakthrough protocol architecture for ultra-low-latency, high-bandwidth interconnects powering AI superclusters and quantum simulation networks
Author-email: Krishna Bajpai <bajpaikrishna715@gmail.com>
Maintainer-email: Krishna Bajpai <bajpaikrishna715@gmail.com>
License: MIT
Project-URL: Homepage, https://github.com/krish567366/hyper-fabric-interconnect
Project-URL: Documentation, https://krish567366.github.io/hyper-fabric-interconnect/
Project-URL: Repository, https://github.com/krish567366/hyper-fabric-interconnect.git
Project-URL: Bug Tracker, https://github.com/krish567366/hyper-fabric-interconnect/issues
Keywords: networking,protocol,AI,quantum,HPC,interconnect,low-latency,distributed-computing
Classifier: Development Status :: 4 - Beta
Classifier: Intended Audience :: Developers
Classifier: Intended Audience :: Science/Research
Classifier: License :: OSI Approved :: MIT License
Classifier: Operating System :: OS Independent
Classifier: Programming Language :: Python :: 3
Classifier: Programming Language :: Python :: 3.8
Classifier: Programming Language :: Python :: 3.9
Classifier: Programming Language :: Python :: 3.10
Classifier: Programming Language :: Python :: 3.11
Classifier: Programming Language :: Python :: 3.12
Classifier: Topic :: Scientific/Engineering
Classifier: Topic :: System :: Networking
Classifier: Topic :: Software Development :: Libraries :: Python Modules
Requires-Python: >=3.8
License-File: LICENSE
Requires-Dist: asyncio-mqtt>=0.11.0
Requires-Dist: numpy>=1.20.0
Requires-Dist: pydantic>=1.8.0
Requires-Dist: click>=8.0.0
Requires-Dist: networkx>=2.6.0
Requires-Dist: aiofiles>=0.8.0
Requires-Dist: psutil>=5.8.0
Requires-Dist: quantummeta-license>=1.0.0
Provides-Extra: dev
Requires-Dist: pytest>=6.0; extra == "dev"
Requires-Dist: pytest-asyncio>=0.18.0; extra == "dev"
Requires-Dist: pytest-cov>=3.0.0; extra == "dev"
Requires-Dist: black>=22.0.0; extra == "dev"
Requires-Dist: isort>=5.10.0; extra == "dev"
Requires-Dist: flake8>=4.0.0; extra == "dev"
Requires-Dist: mypy>=0.950; extra == "dev"
Provides-Extra: docs
Requires-Dist: mkdocs>=1.4.0; extra == "docs"
Requires-Dist: mkdocs-material>=8.0.0; extra == "docs"
Requires-Dist: mkdocs-mermaid2-plugin>=0.6.0; extra == "docs"
Provides-Extra: ml
Requires-Dist: scikit-learn>=1.0.0; extra == "ml"
Requires-Dist: torch>=1.11.0; extra == "ml"
Dynamic: license-file
